wikicli/__init__.py
wikicli/__main__.py
wikicli/wikisearch.py
wikicli-0.1.dist-info/LICENSE
wikicli-0.1.dist-info/METADATA
wikicli-0.1.dist-info/WHEEL
wikicli-0.1.dist-info/entry_points.txt
wikicli-0.1.dist-info/top_level.txt
wikicli-0.1.dist-info/RECORD
