Metadata-Version: 2.1
Name: wikicli
Version: 0.1
Summary: A simple CLI for Wikipedia
Home-page: https://github.com/m1ghtfr3e/Wikipedia-Search-CLI
Author: m1ghtfr3e
Author-email: UNKNOWN
License: UNKNOWN
Keywords: cli wikipedia python
Platform: UNKNOWN
Classifier: Development Status :: 2 - Pre-Alpha
Classifier: Programming Language :: Python :: 3
Classifier: Operating System :: OS Independent
Requires-Dist: bs4
Requires-Dist: requests
